{"tags.md":"8bN3jjKW","archives.md":"BV40tqGi","posts_typescript_typescript中的问号.md":"BkFBwK_K","posts_算法_常用数组排序.md":"DS1Wg74R","index.md":"D1wHych-","readme.md":"B0MfCOGc","posts_打包、工程化_webpack工作流.md":"DMfgBj-v","posts_javascript_原型、原型链.md":"Cwf12YcQ","posts_javascript_js实现链式调用.md":"DF6ow9IR","posts_react_如何封装自己的react hooks.md":"C4LjK50D","posts_react_实现react组件的递归调用.md":"D5o_SBUj","posts_javascript_发布订阅与观察者模式.md":"CG39wiby","posts_typescript_【training】类型标记 pick 与 omit.md":"UIed2DRo","posts_剪贴板_代码整洁之道.md":"CD4jGX_w"}
